{
  "created_utc": "2026-07-21T09:40:00.933268+00:00",
  "symbols": [
    {
      "symbol": "BNB/USDT",
      "scan_count": 78,
      "decision_count": 0,
      "complete_evaluations": 0,
      "paper_trades": 0,
      "closed_paper_trades": 0,
      "latest_side": "LONG",
      "latest_recommendation": "MONITOR",
      "latest_mtf": "LONG",
      "avg_score": 38.6795,
      "avg_confidence": 33.5513,
      "avg_opportunity": 13.4711,
      "max_opportunity": 69.7,
      "avg_rr": 0.237,
      "best_rr": 2.5,
      "directional_win_rate": 0.0,
      "target_1_hit_rate": 0.0,
      "avg_24h_return_pct": 0.0,
      "paper_win_rate": 0.0,
      "paper_expectancy_r": 0.0,
      "paper_profit_factor": 0.0,
      "actionable_rate": 0.0,
      "monitor_rate": 6.41,
      "ignore_rate": 41.03,
      "dominant_side": "NEUTRAL",
      "dominant_recommendation": "IGNORE",
      "memory_status": "OBSERVATION_ACTIVE",
      "confidence": "LOW_MEDIUM",
      "notes": [
        "نماد در حال رصد است اما هنوز Edge کافی ندارد."
      ],
      "blockers": [
        "Complete evaluations کمتر از 30 است: 0",
        "Closed paper trades کمتر از 30 است: 0"
      ]
    },
    {
      "symbol": "BTC/USDT",
      "scan_count": 78,
      "decision_count": 95,
      "complete_evaluations": 92,
      "paper_trades": 0,
      "closed_paper_trades": 0,
      "latest_side": "LONG",
      "latest_recommendation": "MONITOR",
      "latest_mtf": "LONG",
      "avg_score": 37.8077,
      "avg_confidence": 32.2949,
      "avg_opportunity": 17.1665,
      "max_opportunity": 89.5,
      "avg_rr": 0.2459,
      "best_rr": 2.31,
      "directional_win_rate": 63.04,
      "target_1_hit_rate": 38.04,
      "avg_24h_return_pct": 0.477,
      "paper_win_rate": 0.0,
      "paper_expectancy_r": 0.0,
      "paper_profit_factor": 0.0,
      "actionable_rate": 0.0,
      "monitor_rate": 6.41,
      "ignore_rate": 41.03,
      "dominant_side": "NEUTRAL",
      "dominant_recommendation": "IGNORE",
      "memory_status": "SYMBOL_EDGE_EARLY",
      "confidence": "MEDIUM",
      "notes": [
        "Decision edge اولیه برای این نماد مثبت است."
      ],
      "blockers": [
        "Closed paper trades کمتر از 30 است: 0"
      ]
    },
    {
      "symbol": "DOGE/USDT",
      "scan_count": 78,
      "decision_count": 0,
      "complete_evaluations": 0,
      "paper_trades": 0,
      "closed_paper_trades": 0,
      "latest_side": "LONG",
      "latest_recommendation": "MONITOR",
      "latest_mtf": "LONG",
      "avg_score": 39.6923,
      "avg_confidence": 34.4744,
      "avg_opportunity": 18.3438,
      "max_opportunity": 76.4,
      "avg_rr": 0.2951,
      "best_rr": 2.31,
      "directional_win_rate": 0.0,
      "target_1_hit_rate": 0.0,
      "avg_24h_return_pct": 0.0,
      "paper_win_rate": 0.0,
      "paper_expectancy_r": 0.0,
      "paper_profit_factor": 0.0,
      "actionable_rate": 0.0,
      "monitor_rate": 11.54,
      "ignore_rate": 35.9,
      "dominant_side": "NEUTRAL",
      "dominant_recommendation": "IGNORE",
      "memory_status": "OBSERVATION_ACTIVE",
      "confidence": "LOW_MEDIUM",
      "notes": [
        "نماد در حال رصد است اما هنوز Edge کافی ندارد."
      ],
      "blockers": [
        "Complete evaluations کمتر از 30 است: 0",
        "Closed paper trades کمتر از 30 است: 0"
      ]
    },
    {
      "symbol": "ETH/USDT",
      "scan_count": 78,
      "decision_count": 0,
      "complete_evaluations": 0,
      "paper_trades": 0,
      "closed_paper_trades": 0,
      "latest_side": "NEUTRAL",
      "latest_recommendation": "IGNORE",
      "latest_mtf": "LONG",
      "avg_score": 37.5769,
      "avg_confidence": 31.8333,
      "avg_opportunity": 15.4543,
      "max_opportunity": 87.65,
      "avg_rr": 0.1959,
      "best_rr": 2.36,
      "directional_win_rate": 0.0,
      "target_1_hit_rate": 0.0,
      "avg_24h_return_pct": 0.0,
      "paper_win_rate": 0.0,
      "paper_expectancy_r": 0.0,
      "paper_profit_factor": 0.0,
      "actionable_rate": 0.0,
      "monitor_rate": 6.41,
      "ignore_rate": 41.03,
      "dominant_side": "NEUTRAL",
      "dominant_recommendation": "IGNORE",
      "memory_status": "OBSERVATION_ACTIVE",
      "confidence": "LOW_MEDIUM",
      "notes": [
        "نماد در حال رصد است اما هنوز Edge کافی ندارد."
      ],
      "blockers": [
        "Complete evaluations کمتر از 30 است: 0",
        "Closed paper trades کمتر از 30 است: 0"
      ]
    },
    {
      "symbol": "SOL/USDT",
      "scan_count": 78,
      "decision_count": 0,
      "complete_evaluations": 0,
      "paper_trades": 0,
      "closed_paper_trades": 0,
      "latest_side": "LONG",
      "latest_recommendation": "MONITOR",
      "latest_mtf": "NEUTRAL",
      "avg_score": 36.2564,
      "avg_confidence": 31.0,
      "avg_opportunity": 22.01,
      "max_opportunity": 79.4,
      "avg_rr": 0.3451,
      "best_rr": 2.32,
      "directional_win_rate": 0.0,
      "target_1_hit_rate": 0.0,
      "avg_24h_return_pct": 0.0,
      "paper_win_rate": 0.0,
      "paper_expectancy_r": 0.0,
      "paper_profit_factor": 0.0,
      "actionable_rate": 0.0,
      "monitor_rate": 11.54,
      "ignore_rate": 35.9,
      "dominant_side": "NEUTRAL",
      "dominant_recommendation": "IGNORE",
      "memory_status": "OBSERVATION_ACTIVE",
      "confidence": "LOW_MEDIUM",
      "notes": [
        "نماد در حال رصد است اما هنوز Edge کافی ندارد."
      ],
      "blockers": [
        "Complete evaluations کمتر از 30 است: 0",
        "Closed paper trades کمتر از 30 است: 0"
      ]
    },
    {
      "symbol": "XRP/USDT",
      "scan_count": 78,
      "decision_count": 0,
      "complete_evaluations": 0,
      "paper_trades": 0,
      "closed_paper_trades": 0,
      "latest_side": "LONG",
      "latest_recommendation": "MONITOR",
      "latest_mtf": "LONG",
      "avg_score": 34.5897,
      "avg_confidence": 28.6538,
      "avg_opportunity": 17.4057,
      "max_opportunity": 78.25,
      "avg_rr": 0.3378,
      "best_rr": 4.0,
      "directional_win_rate": 0.0,
      "target_1_hit_rate": 0.0,
      "avg_24h_return_pct": 0.0,
      "paper_win_rate": 0.0,
      "paper_expectancy_r": 0.0,
      "paper_profit_factor": 0.0,
      "actionable_rate": 0.0,
      "monitor_rate": 7.69,
      "ignore_rate": 39.74,
      "dominant_side": "NEUTRAL",
      "dominant_recommendation": "IGNORE",
      "memory_status": "OBSERVATION_ACTIVE",
      "confidence": "LOW_MEDIUM",
      "notes": [
        "نماد در حال رصد است اما هنوز Edge کافی ندارد."
      ],
      "blockers": [
        "Complete evaluations کمتر از 30 است: 0",
        "Closed paper trades کمتر از 30 است: 0"
      ]
    }
  ],
  "portfolio_status": "MEMORY_BUILDING",
  "best_memory_symbol": "BTC/USDT",
  "best_paper_symbol": "NONE",
  "total_symbols": 6,
  "total_scans": 468,
  "total_complete_evaluations": 92,
  "total_closed_paper_trades": 0,
  "notes": [],
  "warnings": [
    "Closed paper trades کل پورتفو کمتر از 30 است: 0"
  ]
}